{"nodes": [{"id": "d_codeproject_aamapp_scripts_restore_db_sh", "label": "restore-db.sh", "file_type": "code", "source_file": "scripts/restore-db.sh", "source_location": "L1", "metadata": {"language": "bash", "kind": "file"}}, {"id": "d_codeproject_aamapp_scripts_restore_db_sh__entry", "label": "restore-db.sh script", "file_type": "code", "source_file": "scripts/restore-db.sh", "source_location": "L1", "metadata": {"language": "bash", "kind": "bash_entrypoint"}}], "edges": [{"source": "d_codeproject_aamapp_scripts_restore_db_sh", "target": "d_codeproject_aamapp_scripts_restore_db_sh__entry", "relation": "contains", "confidence": "EXTRACTED", "source_file": "scripts/restore-db.sh", "source_location": "L1", "weight": 1.0}]}